tsbenchmark/__init__.py
tsbenchmark/api.py
tsbenchmark/benchmark.py
tsbenchmark/callbacks.py
tsbenchmark/cfg.py
tsbenchmark/cli.py
tsbenchmark/consts.py
tsbenchmark/datasets.py
tsbenchmark/metrics.py
tsbenchmark/players.py
tsbenchmark/reporter.py
tsbenchmark/run_py.sh
tsbenchmark/server.py
tsbenchmark/tasks.py
tsbenchmark/tsloader.py
tsbenchmark/util.py
tsbenchmark/core/__init__.py
tsbenchmark/core/loader.py
tsbenchmark/tests/__init__.py
tsbenchmark/tests/benchmark_factory.py
tsbenchmark/tests/run_benchmark.py
tsbenchmark/tests/test_api.py
tsbenchmark/tests/test_benchmark.py
tsbenchmark/tests/test_cfg.py
tsbenchmark/tests/test_doc.py
tsbenchmark/tests/test_metrics.py
tsbenchmark/tests/test_players.py
tsbenchmark/tests/test_reporter.py
tsbenchmark/tests/test_runpy.py
tsbenchmark/tests/test_tasks.py
tsbenchmark/tests/test_tsloader.py
tsbenchmark/tests/players/__init__.py
tsbenchmark/tests/players/am_autots_player/__init__.py
tsbenchmark/tests/players/am_autots_player/exec.py
tsbenchmark/tests/players/am_fedot_player/__init__.py
tsbenchmark/tests/players/am_fedot_player/exec.py
tsbenchmark/tests/players/am_pyaf_player/__init__.py
tsbenchmark/tests/players/am_pyaf_player/exec.py
tsbenchmark/tests/players/check_cache_path_player/__init__.py
tsbenchmark/tests/players/check_cache_path_player/exec.py
tsbenchmark/tests/players/hyperts_dl_player/__init__.py
tsbenchmark/tests/players/hyperts_dl_player/exec.py
tsbenchmark/tests/players/hyperts_stat_player/__init__.py
tsbenchmark/tests/players/hyperts_stat_player/exec.py
tsbenchmark/tests/players/non_random_player_univariate/__init__.py
tsbenchmark/tests/players/non_random_player_univariate/exec.py
tsbenchmark/tests/players/plain_navie_player/__init__.py
tsbenchmark/tests/players/plain_navie_player/exec.py
tsbenchmark/tests/players/plain_player/__init__.py
tsbenchmark/tests/players/plain_player/exec.py
tsbenchmark/tests/players/plain_player_conda_yaml/__init__.py
tsbenchmark/tests/players/plain_player_conda_yaml/exec.py
tsbenchmark-0.1.0.dist-info/LICENSE
tsbenchmark-0.1.0.dist-info/METADATA
tsbenchmark-0.1.0.dist-info/WHEEL
tsbenchmark-0.1.0.dist-info/entry_points.txt
tsbenchmark-0.1.0.dist-info/top_level.txt
tsbenchmark-0.1.0.dist-info/RECORD
