Metadata-Version: 2.1
Name: tsbenchmark
Version: 0.1.0
Summary: A benchmarking framework for time series 
Home-page: UNKNOWN
Author: DataCanvas Community
Author-email: yangjian@zetyun.com
License: Apache License 2.0
Platform: UNKNOWN
Classifier: Operating System :: OS Independent
Classifier: Intended Audience :: Developers
Classifier: Intended Audience :: Education
Classifier: Intended Audience :: Science/Research
Classifier: Programming Language :: Python
Classifier: Programming Language :: Python :: 3.6
Classifier: Programming Language :: Python :: 3.7
Classifier: Programming Language :: Python :: 3.8
Classifier: Topic :: Scientific/Engineering
Classifier: Topic :: Scientific/Engineering :: Artificial Intelligence
Classifier: Topic :: Software Development
Classifier: Topic :: Software Development :: Libraries
Classifier: Topic :: Software Development :: Libraries :: Python Modules
Requires-Python: >=3.6.*
License-File: LICENSE
Requires-Dist: hypernets (>=0.2.5.4)
Requires-Dist: pandas
Requires-Dist: scikit-learn
Requires-Dist: pyyaml
Requires-Dist: requests
Provides-Extra: all
Requires-Dist: pytest ; extra == 'all'
Provides-Extra: tests
Requires-Dist: pytest ; extra == 'tests'
